miniolite/FileSQLite.py
miniolite/__init__.py
miniolite/sqlite_tool/base.py
miniolite-0.0.0.3.dist-info/LICENSE
miniolite-0.0.0.3.dist-info/METADATA
miniolite-0.0.0.3.dist-info/WHEEL
miniolite-0.0.0.3.dist-info/top_level.txt
miniolite-0.0.0.3.dist-info/zip-safe
miniolite-0.0.0.3.dist-info/RECORD
